LICENSE
README.md
setup.py
gcode2zaxe/__init__.py
gcode2zaxe/cli.py
gcode2zaxe/lib.py
gcode2zaxe.egg-info/PKG-INFO
gcode2zaxe.egg-info/SOURCES.txt
gcode2zaxe.egg-info/dependency_links.txt
gcode2zaxe.egg-info/entry_points.txt
gcode2zaxe.egg-info/requires.txt
gcode2zaxe.egg-info/top_level.txt