Metadata-Version: 2.1
Name: gcode2zaxe
Version: 2022.6.25
Summary: Gcode to Zaxe Converter | executable: g2z
Home-page: https://github.com/egeakman/gcode2zaxe
Download-URL: https://github.com/egeakman/gcode2zaxe/archive/2022.6.25.tar.gz
Author: Ege Akman
Author-email: egeakmanegeakman@hotmail.com
License: AGPLv3
Project-URL: Homepage, https://github.com/egeakman/gcode2zaxe
Project-URL: Issues, https://github.com/egeakman/gcode2zaxe/issues
Keywords: 3D,gcode,Zaxe,converter,gcode2zaxe,slicer,model,reverse engineering
Classifier: Topic :: Utilities
Classifier: Programming Language :: Python :: 3 :: Only
Classifier: Development Status :: 5 - Production/Stable
Classifier: Environment :: Console
Classifier: License :: OSI Approved :: GNU Affero General Public License v3 or later (AGPLv3+)
Classifier: Operating System :: Microsoft :: Windows
Classifier: Operating System :: POSIX :: Linux
Classifier: Operating System :: MacOS :: MacOS X
Requires-Python: >=3.8
License-File: LICENSE
